PyEventsEmitter/Emitter.py
PyEventsEmitter/__init__.py
PyEventsEmitter/utils.py
PyEventsEmitter-0.0.3.dist-info/LICENSE
PyEventsEmitter-0.0.3.dist-info/METADATA
PyEventsEmitter-0.0.3.dist-info/WHEEL
PyEventsEmitter-0.0.3.dist-info/top_level.txt
PyEventsEmitter-0.0.3.dist-info/RECORD
