Metadata-Version: 2.1
Name: PyEventsEmitter
Version: 0.0.3
Summary: Powerful and flexible EventEmitter implementation with advanced features.
Home-page: https://github.com/HackerX7889/PyEventsEmitter
Author: HackerX
Keywords: EventEmitter,PyEventsEmitter,Emitter,Events
Classifier: Programming Language :: Python :: 3
Classifier: License :: OSI Approved :: MIT License
Classifier: Operating System :: OS Independent
License-File: LICENSE
